{"SUjfMe/29gFeok/iNwjkHw==":"2019-05-31-124025.jpg","fB1VcFCk9IAFidJsj0wyhw==":"2018-08-09-132811.jpg","BoTqQDGcHCbUHDUcsprpEQ==":"2019-06-08-153836.jpg","HjwraRSMYNc9g8a2AuT78A==":"2019-05-31.jpeg","q4J0GzwPxY9GfZeINZ++rA==":"img-787.jpg","bknlu4B6C1eXQvfCadtx5Q==":"img-787.jpeg","W+iYZ9AqjVFndjZp6rqGpw==":"2019-06-8.jpeg","JtOhb5ep3n1bPnRKJ++zCA==":"img-1197.jpg","5vMkk/NQPEuozsdnvsDM7A==":"img-1197.jpeg","RtkR5xCm/qKUC2Nst9SEIA==":"mbr.jpg","DcWzwzIdmGyFrZDRDE6Z1w==":"mbr.png","HqyEJ9BdUMUVZIq7oQJiww==":"mbr.jpeg","LDSKp0hXYCCteGaYUymvMw==":"mbr-1.jpeg","VSstDIjbHAgD590K8Sb6yw==":"mbr-2.jpeg","Nq1gjhykmTgxM9GJtXKXyQ==":"mbr-1.jpg","/tlXi4nS0UDlN7p+CBcnhQ==":"mbr-2.jpg","Mfchqw+h0QjqNfiUbtLHqQ==":"mbr-3.jpg","PqKwOzOeIpvNef77x6Jd1g==":"mbr-4.jpg","Yunvv33ig5qpeIROND2RoQ==":"mbr-5.jpg","EhMQ2KpI90FJMR2iAFKuQg==":"mbr-1.png","GxwbxGqnLMtHIi58DeXNog==":"mbr-2.png","Z5w8krEZQ/UI8i0nbmhSnw==":"img-1198.jpeg","Yt94/n9n4lY3ORGRQOur3g==":"mbr-3.png","sPH/UPwF/IVc29iAQ1UV6A==":"mbr-4.png","TS1PXJvtcPbGTWGhkrI1eg==":"mbr-5.png"}